zen_logs_client/__init__.py
zen_logs_client/client.py
zen_logs_client/exceptions.py
zen_logs_client/py.typed
zen_logs_client/types.py
zen_logs_client-0.1.0.dist-info/METADATA
zen_logs_client-0.1.0.dist-info/WHEEL
zen_logs_client-0.1.0.dist-info/licenses/LICENSE
zen_logs_client-0.1.0.dist-info/RECORD
