Metadata-Version: 2.4
Name: zen-logs-client
Version: 0.1.0
Summary: Async Python client for Zen Logs ingestion endpoints
Project-URL: Homepage, https://github.com/nomie7/zen_logs_python_client
Project-URL: Repository, https://github.com/nomie7/zen_logs_python_client.git
Project-URL: Documentation, https://github.com/nomie7/zen_logs_python_client#readme
Author: nomie7
License-Expression: Apache-2.0
License-File: LICENSE
Keywords: async,logging,logs,observability,telemetry,zen-logs
Classifier: Development Status :: 4 - Beta
Classifier: Framework :: AsyncIO
Classifier: Intended Audience :: Developers
Classifier: License :: OSI Approved :: Apache Software License
Classifier: Programming Language :: Python :: 3
Classifier: Programming Language :: Python :: 3.10
Classifier: Programming Language :: Python :: 3.11
Classifier: Programming Language :: Python :: 3.12
Classifier: Typing :: Typed
Requires-Python: >=3.10
Requires-Dist: httpx>=0.25.0
Provides-Extra: dev
Requires-Dist: mypy>=1.0; extra == 'dev'
Requires-Dist: pytest-asyncio>=0.21.0; extra == 'dev'
Requires-Dist: pytest-cov>=4.0; extra == 'dev'
Requires-Dist: pytest>=7.0; extra == 'dev'
Requires-Dist: respx>=0.20.0; extra == 'dev'
Requires-Dist: ruff>=0.1.0; extra == 'dev'
